[
    {
      "title": "Drywall",
      "price": 400,
      "description": "hello"
    },
    {
      "title": "Wallpaper Removal",
      "price": 750,
      "description": "hello"
    },
    {
      "title": "Water Damage Repairs",
      "price": 2000,
      "description": "hello"
    },
    {
      "title": "Re-caulking",
      "price": 250,
      "description": "hello"
    },
    {
      "title": "Deck Maintenance",
      "price": 700,
      "description": "hello"
    },
    {
      "title": "Wood Rot Repair",
      "price": 200,
      "description": "hello"
    },
    {
      "title": "Ceiling Repair",
      "price": 750,
      "description": "hello"
    },
    {
      "title": "Repair of Screens",
      "price": 110,
      "description": "hello"
    },
    {
      "title": "Kitchen Renovation",
      "price": 20000,
      "description": "hello"
    },
    {
      "title": "Bathroom Renovation",
      "price": 35000,
      "description": "hello"
    },
    {
      "title": "Bedroom Renovation",
      "price": 7900,
      "description": "hello"
    },
    {
      "title": "Flooring",
      "price": 5000,
      "description": "hello"
    },
    {
      "title": "Basement Finishing",
      "price": 50000,
      "description": "hello"
    },
    {
      "title": "Closet Organization Systems",
      "price": 1500,
      "description": "hello"
    },
    {
      "title": "Painting",
      "price": 500,
      "description": "hello"
    },
    {
      "title": "Bi-fold Doors Installation",
      "price": 130,
      "description": "hello"
    },
    {
      "title": "Exhaust Fans Installation",
      "price": 100,
      "description": "hello"
    },
    {
      "title": "Garbage Disposal Installation",
      "price": 100,
      "description": "hello"
    },
    {
      "title": "Glass Installation",
      "price": 50,
      "description": "hello"
    },
    {
      "title": "Window Treatments",
      "price": 110,
      "description": "hello"
    },
    {
      "title": "Handicap Accessibility",
      "price": 1000,
      "description": "hello"
    },
    {
      "title": "Shelving",
      "price": 360,
      "description": "hello"
    },
    {
      "title": "Wall Mounting of TVs",
      "price": 100,
      "description": "hello"
    },
    {
      "title": "Windows Installation",
      "price": 100,
      "description": "hello"
    },
    {
      "title": "Child proofing",
      "price": 500,
      "description": "hello"
    },
    {
      "title": "Pet Doors",
      "price": 200,
      "description": "hello"
    },
    {
      "title": "Window Air Conditioning",
      "price": 300,
      "description": "hello"
    },
    {
      "title": "Smoke Detectors",
      "price": 100,
      "description": "hello"
    },
    {
      "title": "Mailboxes",
      "price": 285,
      "description": "hello"
    },
    {
      "title": "Winterizing",
      "price": 200,
      "description": "hello"
    },
    {
      "title": "Driveway Sealing",
      "price": 300,
      "description": "hello"
    }
  ]
